onyxpm/__init__.py
onyxpm/CLASSES/__init__.py
onyxpm/CLASSES/EnvConfElement.py
onyxpm/CLASSES/NxComponant.py
onyxpm/CLASSES/NxComponantAttributes.py
onyxpm/CLASSES/NxOnyxApi.py
onyxpm/CLASSES/NxProject.py
onyxpm/CLASSES/NxTenant.py
onyxpm/LIBS_BUS/__init__.py
onyxpm/LIBS_BUS/apply_transco.py
onyxpm/LIBS_BUS/compare_onyx_projects.py
onyxpm/LIBS_BUS/find_onyx_project.py
onyxpm/LIBS_BUS/load_env.py
onyxpm/LIBS_BUS/read_onyx_project_api.py
onyxpm/LIBS_BUS/read_onyx_project_package.py
onyxpm/LIBS_BUS/write_to_disk_onyx_project.py
onyxpm/LIBS_CLI/__init__.py
onyxpm/LIBS_CLI/action_1.py
onyxpm/LIBS_CLI/action_2.py
onyxpm/LIBS_CLI/action_3.py
onyxpm/LIBS_CLI/action_4.py
onyxpm/LIBS_CLI/action_5.py
onyxpm/LIBS_CLI/ask_package.py
onyxpm/LIBS_CLI/ask_project.py
onyxpm/LIBS_CLI/ask_tenant.py
onyxpm/LIBS_CLI/check_project_existence.py
onyxpm/LIBS_CLI/clear_screen.py
onyxpm/LIBS_CLI/cli_add_to_workflow.py
onyxpm/LIBS_CLI/cli_connect_api.py
onyxpm/LIBS_CLI/cli_create_tenant.py
onyxpm/LIBS_CLI/cli_get_connection.py
onyxpm/LIBS_CLI/cli_get_id.py
onyxpm/LIBS_CLI/cli_get_info.py
onyxpm/LIBS_CLI/cli_get_organisation_unit.py
onyxpm/LIBS_CLI/cli_tenant_validation.py
onyxpm/LIBS_CLI/creer_arborescence.py
onyxpm/LIBS_CLI/deploy_oConnections.py
onyxpm/LIBS_CLI/deploy_oDataPipelines.py
onyxpm/LIBS_CLI/deploy_oFileProviders.py
onyxpm/LIBS_CLI/deploy_oForms.py
onyxpm/LIBS_CLI/deploy_oNotifications.py
onyxpm/LIBS_CLI/deploy_oPipelineColumns.py
onyxpm/LIBS_CLI/deploy_oReports.py
onyxpm/LIBS_CLI/deploy_oShellScripts.py
onyxpm/LIBS_CLI/deploy_oSqlScripts.py
onyxpm/LIBS_CLI/deploy_oVariables.py
onyxpm/LIBS_CLI/deploy_oWidgetButton.py
onyxpm/LIBS_CLI/deploy_oWidgetFilter.py
onyxpm/LIBS_CLI/deploy_oWidgets.py
onyxpm/LIBS_CLI/deploy_oWorkFlows.py
onyxpm/LIBS_CLI/deploy_oWorkFlowStep.py
onyxpm/LIBS_CLI/display_env.py
onyxpm/LIBS_CLI/exist_envconf.py
onyxpm/LIBS_CLI/exist_tenantName.py
onyxpm/LIBS_CLI/get_connection_name.py
onyxpm/LIBS_CLI/get_envconf.py
onyxpm/LIBS_CLI/get_tenantname.py
onyxpm-0.0.28.dist-info/METADATA
onyxpm-0.0.28.dist-info/WHEEL
onyxpm-0.0.28.dist-info/RECORD
